parakeet_dictation/__init__.py
parakeet_dictation/logger_config.py
parakeet_dictation/main.py
parakeet_dictation/text_selection.py
parakeet_dictation-0.1.6.dist-info/licenses/LICENSE
parakeet_dictation-0.1.6.dist-info/METADATA
parakeet_dictation-0.1.6.dist-info/WHEEL
parakeet_dictation-0.1.6.dist-info/entry_points.txt
parakeet_dictation-0.1.6.dist-info/top_level.txt
parakeet_dictation-0.1.6.dist-info/RECORD
